oneneuron/__init__.py
oneneuron/perceptron.py
oneNeuron_pypi_rajvin_cn-0.0.1.dist-info/LICENSE
oneNeuron_pypi_rajvin_cn-0.0.1.dist-info/METADATA
oneNeuron_pypi_rajvin_cn-0.0.1.dist-info/WHEEL
oneNeuron_pypi_rajvin_cn-0.0.1.dist-info/top_level.txt
oneNeuron_pypi_rajvin_cn-0.0.1.dist-info/RECORD
