Metadata-Version: 2.1
Name: oneNeuron-pypi-rajvin-cn
Version: 0.0.1
Summary: Implementation of a simple Perceptron
Home-page: https://github.com/rajvin-cn/oneNeuron_pypi
Author: rajvin-cn
Author-email: rajvin.k2020@gmail.com
License: UNKNOWN
Project-URL: Bug Tracker, https://github.com/rajvin-cn/oneNeuron_pypi/issues
Platform: UNKNOWN
Classifier: Programming Language :: Python :: 3
Classifier: License :: OSI Approved :: MIT License
Classifier: Operating System :: OS Independent
Requires-Python: >=3.7
License-File: LICENSE
Requires-Dist: numpy
Requires-Dist: tqdm
